querypp.py
querypp-0.1.2.dist-info/COPYING
querypp-0.1.2.dist-info/METADATA
querypp-0.1.2.dist-info/WHEEL
querypp-0.1.2.dist-info/top_level.txt
querypp-0.1.2.dist-info/RECORD
