Metadata-Version: 2.1
Name: querypp
Version: 0.1.2
Summary: SQL query templating shorthand
Home-page: https://github.com/bmintz/querypp
Author: Benjamin Mintz
Author-email: bmintz@protonmail.com
License: CC0 1.0
Platform: UNKNOWN
Classifier: Topic :: Software Development
Classifier: License :: CC0 1.0 Universal (CC0 1.0) Public Domain Dedication
Classifier: Programming Language :: Python :: 3 :: Only
Classifier: Programming Language :: Python :: 3.5
Classifier: Programming Language :: Python :: 3.6
Classifier: Programming Language :: Python :: 3.7
Classifier: Programming Language :: Python :: 3.8
Requires-Dist: jinja2 (<3.0.0,>=2.10.1)
